{
  "puzzleId": 2412483,
  "width": 20,
  "height": 20,
  "row_hints": [
    [
      2,
      2,
      2,
      1
    ],
    [
      2,
      4,
      4
    ],
    [
      1,
      4,
      1,
      4
    ],
    [
      1,
      3,
      6,
      4
    ],
    [
      7,
      3,
      4
    ],
    [
      12
    ],
    [
      12
    ],
    [
      10
    ],
    [
      11,
      2
    ],
    [
      7,
      2
    ],
    [
      5,
      3,
      1
    ],
    [
      4,
      5
    ],
    [
      1,
      2,
      4
    ],
    [
      4,
      6
    ],
    [
      3,
      4,
      1
    ],
    [
      2,
      1,
      6
    ],
    [
      1,
      1,
      3
    ],
    [
      6,
      3
    ],
    [
      7,
      2,
      1
    ],
    [
      9,
      2,
      2
    ]
  ],
  "col_hints": [
    [
      5,
      1
    ],
    [
      4,
      4,
      2
    ],
    [
      8,
      3
    ],
    [
      9,
      3
    ],
    [
      2,
      8,
      3,
      3
    ],
    [
      10,
      7
    ],
    [
      6,
      3,
      3
    ],
    [
      5,
      2,
      4
    ],
    [
      4,
      1,
      1
    ],
    [
      2,
      4,
      2
    ],
    [
      8,
      4
    ],
    [
      8,
      6
    ],
    [
      7,
      9
    ],
    [
      1,
      1,
      9
    ],
    [
      2,
      5
    ],
    [
      2,
      1,
      1
    ],
    [
      5,
      3,
      1
    ],
    [
      5
    ],
    [
      4,
      1
    ],
    [
      5,
      1,
      2
    ]
  ],
  "scraped_at": "2026-02-27T18:29:35.265Z"
}